fec_reader/__init__.py
fec_reader/conf.py
fec_reader/db.py
fec_reader/fec.db
fec_reader/get.py
fec_reader/util.py
fec_reader-2.1.1.dist-info/LICENSE
fec_reader-2.1.1.dist-info/METADATA
fec_reader-2.1.1.dist-info/WHEEL
fec_reader-2.1.1.dist-info/top_level.txt
fec_reader-2.1.1.dist-info/RECORD
