Metadata-Version: 2.1
Name: fec-reader
Version: 2.1.1
Summary: retrieves data from FEC.gov website
Home-page: https://github.com/alexus888/fec-reader
Author: Alexus Wong
Author-email: alexus888@gmail.com
License: UNKNOWN
Platform: UNKNOWN
Classifier: Programming Language :: Python :: 3
Classifier: License :: OSI Approved :: MIT License
Classifier: Operating System :: OS Independent
Requires-Dist: requests
Requires-Dist: pandas
Requires-Dist: lxml
Requires-Dist: html5lib
Requires-Dist: sqlalchemy
